odoo8_addon_hw_customer_display-8.0.0.1.0-py2.7-nspkg.pth
odoo_addons/hw_customer_display/__openerp__.py
odoo_addons/hw_customer_display/__init__.py
odoo_addons/hw_customer_display/controllers/main.py
odoo_addons/hw_customer_display/controllers/__init__.py
odoo_addons/hw_customer_display/test-scripts/customer-display-test.py
odoo8_addon_hw_customer_display-8.0.0.1.0.dist-info/top_level.txt
odoo8_addon_hw_customer_display-8.0.0.1.0.dist-info/WHEEL
odoo8_addon_hw_customer_display-8.0.0.1.0.dist-info/RECORD
odoo8_addon_hw_customer_display-8.0.0.1.0.dist-info/metadata.json
odoo8_addon_hw_customer_display-8.0.0.1.0.dist-info/DESCRIPTION.rst
odoo8_addon_hw_customer_display-8.0.0.1.0.dist-info/METADATA
odoo8_addon_hw_customer_display-8.0.0.1.0.dist-info/namespace_packages.txt
