Metadata-Version: 2.0
Name: odoo8-addon-hw-customer-display
Version: 8.0.0.1.0
Summary: Adds support for Customer Display in the Point of Sale
Home-page: http://www.akretion.com
Author: UNKNOWN
Author-email: UNKNOWN
License: AGPL-3
Platform: UNKNOWN
Requires-Dist: odoo (<9.0a,>=8.0a)
Requires-Dist: pyserial
Requires-Dist: unidecode
Classifier: Programming Language :: Python :: 2.7
Classifier: Framework :: Odoo
Classifier: License :: OSI Approved :: GNU Affero General Public License v3
